{"loss": 0.6981458689855493, "accuracy": 0.49971671388101985, "time_this_iter_s": 101.88120293617249, "should_checkpoint": true, "done": true, "timesteps_total": null, "episodes_total": null, "training_iteration": 1, "trial_id": "f7641_00012", "experiment_id": "1b2924db4061408c9761225c4a15754f", "date": "2023-04-03_09-13-18", "timestamp": 1680538398, "time_total_s": 101.88120293617249, "pid": 1443, "hostname": "MacBook-Pro-2", "node_ip": "127.0.0.1", "config": {"l1": 8, "l2": 4, "kernel_size": 3, "lr": 0.01688635295412136, "momentum": 0.9056220919301465, "batch_size": 16}, "time_since_restore": 101.88120293617249, "timesteps_since_restore": 0, "iterations_since_restore": 1, "warmup_time": 0.0022809505462646484}
